mcsolver/Lattice.py
mcsolver/WannierKit.py
mcsolver/__init__.py
mcsolver/fileio.py
mcsolver/guiMain.py
mcsolver/heisenberglib.so
mcsolver/input.py
mcsolver/isinglib.so
mcsolver/mcMain.py
mcsolver/toolbox.py
mcsolver/win.py
mcsolver/xylib.so
mcsolver-2.0.1.dist-info/LICENSE
mcsolver-2.0.1.dist-info/METADATA
mcsolver-2.0.1.dist-info/WHEEL
mcsolver-2.0.1.dist-info/top_level.txt
mcsolver-2.0.1.dist-info/RECORD
