Metadata-Version: 2.1
Name: mcsolver
Version: 2.0.1
Summary: A user friendly program to do Monte Carlo sims for magnetic systems
Home-page: https://github.com/golddoushi/mcsolver
Author: Liang Liu
Author-email: liangliu@main.sdu.edu.cn
License: UNKNOWN
Platform: UNKNOWN
Classifier: Programming Language :: Python :: 3
Classifier: License :: OSI Approved :: GNU General Public License v3 (GPLv3)
Classifier: Development Status :: 4 - Beta
Classifier: Operating System :: OS Independent
Classifier: Topic :: Scientific/Engineering :: Physics
Classifier: Topic :: Scientific/Engineering :: Visualization
Requires-Python: >=3.7
Requires-Dist: matplotlib
Requires-Dist: numpy
